MANIFEST.in
README.rst
setup.py
src/UFx.egg-info/PKG-INFO
src/UFx.egg-info/SOURCES.txt
src/UFx.egg-info/dependency_links.txt
src/UFx.egg-info/not-zip-safe
src/UFx.egg-info/top_level.txt
src/ufx/__init__.py
src/ufx/uf_hash.py
src/ufx/uf_tree.py