Metadata-Version: 1.1
Name: UFx
Version: 1.0
Summary: UFx is a pure python library that implements the disjoint-set data structure which allows the union-find operations.
Home-page: UNKNOWN
Author: Philippe Bordron
Author-email: UNKNOWN
License: LGPL
Platform: UNKNOWN
Classifier: Development Status :: 4 - Beta
Classifier: License :: OSI Approved :: GNU Lesser General Public License v3 (LGPLv3)
Classifier: Programming Language :: Python
Classifier: Programming Language :: Python :: 2.7
Classifier: Programming Language :: Python :: 3.4
Classifier: Programming Language :: Python :: 3.5
Classifier: Topic :: Software Development :: Libraries :: Python Modules
Classifier: Operating System :: OS Independent
